proyecto_du/__init__.py
proyecto_du-0.0.1.dist-info/METADATA
proyecto_du-0.0.1.dist-info/WHEEL
proyecto_du-0.0.1.dist-info/top_level.txt
proyecto_du-0.0.1.dist-info/RECORD
