Metadata-Version: 2.4
Name: proyecto-du
Version: 0.0.1
Summary: Data Understanding phase package (CRISP-DM)
Author: Angel Castellanos, Alejandro Azurdia, Diego Morales
Requires-Python: >=3.8
Requires-Dist: proyecto-core==0.0.1
Requires-Dist: pandas>=2.0.0
Requires-Dist: pyyaml>=6.0
Dynamic: author
Dynamic: requires-dist
Dynamic: requires-python
Dynamic: summary
